{
  "shopTokenId": -1,
  "kaTokenId": -1,
  "onePieceTokenId": 100100,
  "soshinaTokenId": 100200,
  "Yatsushika1TokenId": 100300,
  "Yatsushika2TokenId": 100301,
  "Yatsushika3TokenId": 100302,
  "Yatsushika4TokenId": 100303,
  "MaskedKid1TokenId": 100305,
  "MaskedKid2TokenId": 100306,
  "MaskedKid3TokenId": 100307,
  "MaskedKid4TokenId": 100308,
  "Kiyoshi1TokenId": 100310,
  "Kiyoshi2TokenId": 100311,
  "Kiyoshi3TokenId": 100312,
  "Kiyoshi4TokenId": 100313,
  "Amitie1TokenId": 100315,
  "Amitie2TokenId": 100316,
  "Amitie3TokenId": 100317,
  "Amitie4TokenId": 100318,
  "Machina1TokenId": 100320,
  "Machina2TokenId": 100321,
  "Machina3TokenId": 100322,
  "Machina4TokenId": 100323
}